petakita/__init__.py
petakita/main.py
petakita-0.1.dist-info/LICENSE
petakita-0.1.dist-info/METADATA
petakita-0.1.dist-info/WHEEL
petakita-0.1.dist-info/entry_points.txt
petakita-0.1.dist-info/top_level.txt
petakita-0.1.dist-info/RECORD
