Metadata-Version: 2.1
Name: petakita
Version: 0.1
Summary: A Petakita package
Home-page: https://github.com/emhayusa/petakita
Author: Muhammad Hasannudin Yusa
Author-email: emhayusa@gmail.com
License: UNKNOWN
Platform: UNKNOWN
Classifier: Programming Language :: Python :: 3
Classifier: License :: OSI Approved :: MIT License
Classifier: Operating System :: OS Independent
Requires-Dist: Click
